{"id":"f7c7b52b-4e68-496e-99cf-4d2db7146b01","timestamp":1740442094300,"matcher":{"static":{},"wildcard":{},"dynamic":{}},"prerendered":["/","/health-check","/admin/orders-management","/admin/products-management","/add-address-to-order","/add-new-address","/admin/admin-panel","/create-invoice","/add-shipping-method-to-order","/steps-to-order","/index_","/admin/users-management","/my-orders","/my-coupons","/my-scores","/register","/login","/my-wallet","/online-payment-method","/select-payment-methods","/your-transaction-receive","/test"]}